README.md
setup.py
no_asyncio/__init__.py
no_asyncio/no_asyncio.py
no_asyncio.egg-info/PKG-INFO
no_asyncio.egg-info/SOURCES.txt
no_asyncio.egg-info/dependency_links.txt
no_asyncio.egg-info/top_level.txt