Metadata-Version: 1.0
Name: no-asyncio
Version: 0.1
Summary: Transparent asyncio methods
Home-page: https://github.com/justinbarrick/no_asyncio
Author: UNKNOWN
Author-email: UNKNOWN
License: UNKNOWN
Platform: UNKNOWN
